setup.py
tsne_animate/__init__.py
tsne_animate.egg-info/PKG-INFO
tsne_animate.egg-info/SOURCES.txt
tsne_animate.egg-info/dependency_links.txt
tsne_animate.egg-info/not-zip-safe
tsne_animate.egg-info/requires.txt
tsne_animate.egg-info/top_level.txt