Metadata-Version: 1.0
Name: tsne-animate
Version: 0.1.3
Summary: Automated animation for scikit-learn's t-sne algorithm
Home-page: https://github.com/hardkun/tsne_animate
Author: Oleksandr Buzynnyi
Author-email: oleksandr.buzynnyi@gmail.com
License: MIT
Platform: UNKNOWN
